reconcile/__init__.py
reconcile/conftest.py
reconcile/forecast.py
reconcile/grouping.py
reconcile/grouping_test.py
reconcile/probabilistic_reconciliation.py
reconcile/reconciliation_test.py
probabilistic_reconciliation-0.2.0.dist-info/METADATA
probabilistic_reconciliation-0.2.0.dist-info/WHEEL
probabilistic_reconciliation-0.2.0.dist-info/licenses/LICENSE
probabilistic_reconciliation-0.2.0.dist-info/RECORD
