Metadata-Version: 2.4
Name: probabilistic-reconciliation
Version: 0.2.0
Summary: Probabilistic reconciliation of time series forecasts
Project-URL: homepage, https://github.com/dirmeier/reconcile
Author-email: Simon Dirmeier <sfyrbnd@pm.me>
License: 
License-File: LICENSE
Keywords: forecasting,hierarchical time series,probabilistic reconciliation,timeseries
Classifier: Development Status :: 3 - Alpha
Classifier: Intended Audience :: Science/Research
Classifier: License :: OSI Approved :: Apache Software License
Classifier: Programming Language :: Python :: 3
Classifier: Programming Language :: Python :: 3.11
Classifier: Programming Language :: Python :: 3.12
Classifier: Programming Language :: Python :: 3.13
Requires-Python: >=3.11
Requires-Dist: blackjax>=1.2.4
Requires-Dist: chex>=0.1.8
Requires-Dist: einops>=0.8.0
Requires-Dist: flax>=0.10.2
Requires-Dist: jax>=0.4.38
Requires-Dist: optax>=0.2.4
Requires-Dist: pandas>=1.5.1
Requires-Dist: ramsey>=0.2.1
Requires-Dist: tfp-nightly[jax]>=0.26.0.dev20241227
